healthharbor_dental_client/__init__.py
healthharbor_dental_client/client.py
healthharbor_dental_client/models.py
tests/__init__.py
tests/test_client.py
healthharbor_dental_client-0.1.0.dist-info/METADATA
healthharbor_dental_client-0.1.0.dist-info/WHEEL
healthharbor_dental_client-0.1.0.dist-info/top_level.txt
healthharbor_dental_client-0.1.0.dist-info/RECORD
