Metadata-Version: 2.1
Name: healthharbor_dental_client
Version: 0.1.0
Summary: An Unofficial client library for interacting with Health Harbor Dental API
Home-page: https://github.com/yourusername/healthharbor_dental_client
Author: Don Johnson
Author-email: donj@zuub.com
Project-URL: Bug Reports, https://github.com/copyleftdev/healthharbor_dental_client/issues
Project-URL: Source, https://github.com/copyleftdev/healthharbor_dental_client
Keywords: healthharbor api dental client
Classifier: Development Status :: 3 - Alpha
Classifier: Intended Audience :: Developers
Classifier: Topic :: Software Development :: Libraries :: Python Modules
Classifier: License :: OSI Approved :: MIT License
Classifier: Programming Language :: Python :: 3
Classifier: Programming Language :: Python :: 3.8
Classifier: Programming Language :: Python :: 3.9
Classifier: Programming Language :: Python :: 3.10
Classifier: Programming Language :: Python :: 3.11
Classifier: Programming Language :: Python :: 3.12
Classifier: Operating System :: OS Independent
Requires-Python: >=3.8
Requires-Dist: requests
